automea/__init__.py
automea/__main__.py
automea/util.py
automea/models/signal100.h5
automea/models/signal30.h5
automea/models/spikes30.h5
automea/training/GUI.py
automea/training/generate_pred_vs_def_bursts.py
automea/training/generate_trainset.py
automea/training/helper.py
automea/training/plot_burst_quality.py
automea/training/plot_custom_accuracy.py
automea/training/split_trainset.py
automea/training/train_models.py
automea-0.0.19.dist-info/METADATA
automea-0.0.19.dist-info/WHEEL
automea-0.0.19.dist-info/top_level.txt
automea-0.0.19.dist-info/RECORD
