Metadata-Version: 2.4
Name: automea
Version: 0.0.19
Summary: Automated analysis of MEA datasets
Author-email: Vinicius Hernandes <viniciusfhernandes@gmail.com>
License: MIT License
Project-URL: Homepage, https://gitlab.com/QMAI/papers/autoMEA
Classifier: Programming Language :: Python :: 3
Classifier: Operating System :: OS Independent
Requires-Python: >=3.10
Requires-Dist: h5py<4.0.0,>=3.7.0
Requires-Dist: matplotlib==3.6.0
Requires-Dist: numpy==1.22.4
Requires-Dist: pandas==1.5.0
Requires-Dist: tensorflow<2.14.0,>=2.13.0
